ai_data/__init__.py
ai_data/data/Ai practical-1.pdf
ai_data/data/balanceScale.csv
ai_data/data/pima-indians-diabetes.data.csv
ai_data/data/requirements.txt
aipracti_data-0.1.dist-info/METADATA
aipracti_data-0.1.dist-info/WHEEL
aipracti_data-0.1.dist-info/top_level.txt
aipracti_data-0.1.dist-info/RECORD
